lightdash_client/__init__.py
lightdash_client/client.py
lightdash_client/errors.py
lightdash_client/py.typed
lightdash_client/types.py
lightdash_client/api/__init__.py
lightdash_client/api/catalog/__init__.py
lightdash_client/api/catalog/create_metrics_tree_edge.py
lightdash_client/api/catalog/delete_metrics_tree_edge.py
lightdash_client/api/catalog/get_analytics.py
lightdash_client/api/catalog/get_analytics_field.py
lightdash_client/api/catalog/get_catalog.py
lightdash_client/api/catalog/get_metadata.py
lightdash_client/api/catalog/get_metric.py
lightdash_client/api/catalog/get_metrics_catalog.py
lightdash_client/api/catalog/get_metrics_tree.py
lightdash_client/api/catalog/get_metrics_with_time_dimensions.py
lightdash_client/api/catalog/get_segment_dimensions.py
lightdash_client/api/catalog/has_metrics_in_catalog.py
lightdash_client/api/catalog/update_catalog_item_icon.py
lightdash_client/api/charts/__init__.py
lightdash_client/api/charts/calculate_total_from_saved_chart.py
lightdash_client/api/charts/download_csv_from_saved_chart.py
lightdash_client/api/charts/get_chart_history.py
lightdash_client/api/charts/get_chart_version.py
lightdash_client/api/charts/get_chart_version_results.py
lightdash_client/api/charts/post_chart_results.py
lightdash_client/api/charts/post_chart_version_rollback.py
lightdash_client/api/charts/post_dashboard_tile.py
lightdash_client/api/charts/promote_chart.py
lightdash_client/api/charts/promote_chart_diff.py
lightdash_client/api/comments/__init__.py
lightdash_client/api/comments/create_comment.py
lightdash_client/api/comments/delete_comment.py
lightdash_client/api/comments/get_comments.py
lightdash_client/api/comments/resolve_comment.py
lightdash_client/api/content/__init__.py
lightdash_client/api/content/get_pinned_items.py
lightdash_client/api/content/update_pinned_items_order.py
lightdash_client/api/dashboards/__init__.py
lightdash_client/api/dashboards/promote_dashboard.py
lightdash_client/api/dashboards/promote_dashboard_diff.py
lightdash_client_python-0.1471.0.dist-info/LICENSE
lightdash_client_python-0.1471.0.dist-info/WHEEL
lightdash_client_python-0.1471.0.dist-info/METADATA
lightdash_client_python-0.1471.0.dist-info/RECORD
